README.md
setup.py
tantum/__init__.py
tantum/enums.py
tantum.egg-info/PKG-INFO
tantum.egg-info/SOURCES.txt
tantum.egg-info/dependency_links.txt
tantum.egg-info/requires.txt
tantum.egg-info/top_level.txt
tantum/callbacks/__init__.py
tantum/callbacks/callbacks.py
tantum/callbacks/early_stopping.py
tantum/callbacks/tensorboard.py
tantum/datasets/__init__.py
tantum/datasets/generic.py
tantum/datasets/image_classification.py
tantum/datasets/mnist.py
tantum/model/__init__.py
tantum/model/model.py
tantum/utils/__init__.py
tantum/utils/average_meter.py