Metadata-Version: 2.1
Name: tantum
Version: 0.0.5
Summary: tantum - train pytorch models
Home-page: https://github.com/dmitryshendryk/tantum
Author: Dmitry Shendryk
Author-email: dmitryshendryk@gmail.com
License: Apache License
Platform: UNKNOWN
Requires-Python: >3.6.2
